data533_supermans/__init__.py
data533_supermans/main.py
data533_supermans/administer/__init__.py
data533_supermans/administer/account.py
data533_supermans/administer/inventory.py
data533_supermans/customer/__init__.py
data533_supermans/customer/members.py
data533_supermans/customer/transactions.py
data533_supermans-0.0.2.dist-info/METADATA
data533_supermans-0.0.2.dist-info/WHEEL
data533_supermans-0.0.2.dist-info/top_level.txt
data533_supermans-0.0.2.dist-info/RECORD
